faster_os.cp38-win_amd64.pyd
faster_os/generic.cp38-win_amd64.pyd
faster_os/path.cp38-win_amd64.pyd
unix/__init__.py
unix/generic.py
unix/path.py
win/__init__.py
win/generic.py
win/path.py
faster_os-0.0.11.dist-info/METADATA
faster_os-0.0.11.dist-info/WHEEL
faster_os-0.0.11.dist-info/top_level.txt
faster_os-0.0.11.dist-info/RECORD
