Metadata-Version: 2.1
Name: faster-os
Version: 0.0.11
Summary: Up to 6700% faster OS module.
Home-page: https://github.com/American-Best-Technologies-Company/faster-os
Author: American Best Technologies Company
Author-email: contact@abtco.us
License: MPL 2.0
Project-URL: Bug Tracker, https://github.com/American-Best-Technologies-Company/faster-os/issues
Project-URL: Our website, http://www.abtco.us
Project-URL: Used by MyQuickMac, http://www.myquickmac.com
Platform: UNKNOWN
Classifier: Development Status :: 5 - Production/Stable
Classifier: License :: OSI Approved :: Mozilla Public License 2.0 (MPL 2.0)
Classifier: Programming Language :: Python :: 3
Classifier: Operating System :: OS Independent
Classifier: Programming Language :: Python :: 3.8
Classifier: Intended Audience :: Developers
Classifier: Programming Language :: Cython
Classifier: Topic :: Office/Business
Classifier: Topic :: Software Development
Classifier: Topic :: Software Development :: Libraries
Classifier: Topic :: Software Development :: Libraries :: Python Modules
Classifier: Topic :: System
Classifier: Topic :: System :: Filesystems
Classifier: Topic :: System :: Operating System
Classifier: Topic :: Utilities
